foggynight
