Metadata-Version: 2.1
Name: foggynight
Version: 2.0.0
Summary: Weather forecast data
Author: Justin Bartoldus
Author-email: jbxbox117@Hotmail.com
Keywords: weather,forecast,openweather
